dhcpkit/__init__.py
dhcpkit/display_strings.py
dhcpkit/protocol_element.py
dhcpkit/registry.py
dhcpkit/utils.py
dhcpkit/common/__init__.py
dhcpkit/common/privileges.py
dhcpkit/common/logging/__init__.py
dhcpkit/common/logging/verbosity.py
dhcpkit/common/server/__init__.py
dhcpkit/common/server/config_datatypes.py
dhcpkit/common/server/config_elements.py
dhcpkit/common/server/logging/__init__.py
dhcpkit/common/server/logging/component.xml
dhcpkit/common/server/logging/config_datatypes.py
dhcpkit/common/server/logging/config_elements.py
dhcpkit/ipv6/__init__.py
dhcpkit/ipv6/duid_registry.py
dhcpkit/ipv6/duids.py
dhcpkit/ipv6/message_registry.py
dhcpkit/ipv6/messages.py
dhcpkit/ipv6/option_registry.py
dhcpkit/ipv6/options.py
dhcpkit/ipv6/utils.py
dhcpkit/ipv6/client/__init__.py
dhcpkit/ipv6/client/test_leasequery.py
dhcpkit/ipv6/extensions/__init__.py
dhcpkit/ipv6/extensions/bulk_leasequery.py
dhcpkit/ipv6/extensions/client_fqdn.py
dhcpkit/ipv6/extensions/dns.py
dhcpkit/ipv6/extensions/dslite.py
dhcpkit/ipv6/extensions/leasequery.py
dhcpkit/ipv6/extensions/linklayer_id.py
dhcpkit/ipv6/extensions/map.py
dhcpkit/ipv6/extensions/ntp.py
dhcpkit/ipv6/extensions/ntp_suboption_registry.py
dhcpkit/ipv6/extensions/pd_exclude.py
dhcpkit/ipv6/extensions/prefix_delegation.py
dhcpkit/ipv6/extensions/relay_echo_request.py
dhcpkit/ipv6/extensions/remote_id.py
dhcpkit/ipv6/extensions/sip_servers.py
dhcpkit/ipv6/extensions/sntp.py
dhcpkit/ipv6/extensions/sol_max_rt.py
dhcpkit/ipv6/extensions/subscriber_id.py
dhcpkit/ipv6/extensions/timezone.py
dhcpkit/ipv6/server/__init__.py
dhcpkit/ipv6/server/config_datatypes.py
dhcpkit/ipv6/server/config_elements.py
dhcpkit/ipv6/server/config_parser.py
dhcpkit/ipv6/server/config_schema.xml
dhcpkit/ipv6/server/control_socket.py
dhcpkit/ipv6/server/dhcpctl.py
dhcpkit/ipv6/server/extension_registry.py
dhcpkit/ipv6/server/generate_config_docs.py
dhcpkit/ipv6/server/main.py
dhcpkit-1.0.7.dist-info/DESCRIPTION.rst
dhcpkit-1.0.7.dist-info/METADATA
dhcpkit-1.0.7.dist-info/RECORD
dhcpkit-1.0.7.dist-info/WHEEL
dhcpkit-1.0.7.dist-info/entry_points.txt
dhcpkit-1.0.7.dist-info/metadata.json
dhcpkit-1.0.7.dist-info/top_level.txt
